soup/__init__.py
soup/_nbdev.py
soup/cli.py
soup/core.py
soup/loading.py
spurs/__init__.py
spurs/_nbdev.py
spurs/cli.py
spurs/core.py
spurs/loading.py
spurs-0.0.2.dist-info/LICENSE
spurs-0.0.2.dist-info/METADATA
spurs-0.0.2.dist-info/WHEEL
spurs-0.0.2.dist-info/entry_points.txt
spurs-0.0.2.dist-info/top_level.txt
spurs-0.0.2.dist-info/RECORD
