Metadata-Version: 2.1
Name: spurs
Version: 0.0.2
Summary: Sparse phase unwrapping for InSAR interferograms
Home-page: https://github.com/scottstanie/spurs/tree/master/
Author: Scott Staniewicz
Author-email: scott.stanie@utexas.edu
License: Apache Software License 2.0
Keywords: insar phase unwrap admm optimization
Platform: UNKNOWN
Classifier: Development Status :: 3 - Alpha
Classifier: Intended Audience :: Science/Research
Classifier: License :: OSI Approved :: Apache Software License
Classifier: Natural Language :: English
Classifier: Programming Language :: Python :: 3.6
Classifier: Programming Language :: Python :: 3.7
Classifier: Programming Language :: Python :: 3.8
Requires-Python: >=3.6
Requires-Dist: scipy
Requires-Dist: numpy
